onedriveintegrate
