Metadata-Version: 2.1
Name: onedriveintegrate
Version: 1.3
Summary: Package for OneDrive File Management
Author: William Guo
License: MIT
